ICalculationManager/__init__.py
ICalculationManager/calculation_manager_pb2.py
ICalculationManager/calculation_manager_pb2_grpc.py
ISimulationNode/__init__.py
ISimulationNode/simulation_node_pb2.py
ISimulationNode/simulation_node_pb2_grpc.py
ICalculationManager_ncn-0.0.23.dist-info/LICENSE
ICalculationManager_ncn-0.0.23.dist-info/METADATA
ICalculationManager_ncn-0.0.23.dist-info/WHEEL
ICalculationManager_ncn-0.0.23.dist-info/top_level.txt
ICalculationManager_ncn-0.0.23.dist-info/RECORD
