Metadata-Version: 2.1
Name: ICalculationManager-ncn
Version: 0.0.23
Summary: Interface files for the Calcualation Manager
Home-page: https://github.com/pypa/sampleproject
Author: Niels Christian Nielsen
Author-email: nielschristiannielsen@gmail.com
License: UNKNOWN
Project-URL: Bug Tracker, https://github.com/pypa/sampleproject/issues
Platform: UNKNOWN
Classifier: Programming Language :: Python :: 3
Classifier: License :: OSI Approved :: MIT License
Classifier: Operating System :: OS Independent
Requires-Python: >=3.8.5
License-File: LICENSE
